{"elements": {"edges": [{"data": {"id": "803570-801311", "ranking": 1, "width": 1, "interaction": "cw", "selected": false, "target": "801311", "source": "803570", "similarity": 0.017902099997831218}}, {"data": {"id": "803570-760716", "ranking": 2, "width": 1, "interaction": "cw", "selected": false, "target": "760716", "source": "803570", "similarity": -0.011628174007526186}}, {"data": {"id": "801311-803570", "ranking": 1, "width": 1, "interaction": "cw", "selected": false, "target": "803570", "source": "801311", "similarity": 0.017902099997831218}}, {"data": {"id": "801311-189844", "ranking": 2, "width": 1, "interaction": "cw", "selected": false, "target": "189844", "source": "801311", "similarity": 0.0004522944504822006}}, {"data": {"id": "760716-600988", "ranking": 1, "width": 28, "interaction": "cw", "selected": false, "target": "600988", "source": "760716", "similarity": 0.6889212560136336}}, {"data": {"id": "760716-761652", "ranking": 2, "width": 26, "interaction": "cw", "selected": false, "target": "761652", "source": "760716", "similarity": 0.6381292970028571}}, {"data": {"id": "760716-761436", "ranking": 3, "width": 26, "interaction": "cw", "selected": false, "target": "761436", "source": "760716", "similarity": 0.6279982043658392}}, {"data": {"id": "760716-764299", "ranking": 4, "width": 23, "interaction": "cw", "selected": false, "target": "764299", "source": "760716", "similarity": 0.570830675634898}}, {"data": {"id": "760716-775124", "ranking": 5, "width": 23, "interaction": "cw", "selected": false, "target": "775124", "source": "760716", "similarity": 0.5584038819511057}}, {"data": {"id": "760716-739341", "ranking": 6, "width": 22, "interaction": "cw", "selected": false, "target": "739341", "source": "760716", "similarity": 0.5476743198952682}}, {"data": {"id": "760716-765226", "ranking": 7, "width": 22, "interaction": "cw", "selected": false, "target": "765226", "source": "760716", "similarity": 0.5369717415526402}}, {"data": {"id": "760716-724284", "ranking": 8, "width": 22, "interaction": "cw", "selected": false, "target": "724284", "source": "760716", "similarity": 0.5363129441135871}}, {"data": {"id": "760716-753790", "ranking": 9, "width": 21, "interaction": "cw", "selected": false, "target": "753790", "source": "760716", "similarity": 0.5185652906504099}}, {"data": {"id": "760716-859143", "ranking": 10, "width": 21, "interaction": "cw", "selected": false, "target": "859143", "source": "760716", "similarity": 0.5028806829794008}}], "nodes": [{"position": {"x": 0, "y": 0}, "data": {"id": "803570", "depth": "0", "selected": false, "name": "\uc720\ub9cc\uc900"}}, {"position": {"x": 100.0, "y": 0.0}, "data": {"id": "801311", "depth": "1", "selected": false, "name": "\ucee4\ud2b8\uc6b0\ub4dc_\uc2a4\ubbf8\uc2a4"}}, {"position": {"x": 80.90169943749474, "y": 58.778525229247315}, "data": {"id": "760716", "depth": "1", "selected": false, "name": "\ud0c0\uce74\ucfe0\ub77c_\ucf04"}}, {"position": {"x": 1000.0, "y": 0.0}, "data": {"id": "803570", "depth": "2", "selected": false, "name": "\uc720\ub9cc\uc900"}}, {"position": {"x": 998.0267284282716, "y": 62.79051952931337}, "data": {"id": "189844", "depth": "2", "selected": false, "name": "\uc774\uc644\ud638"}}, {"position": {"x": 809.0169943749474, "y": 587.7852522924732}, "data": {"id": "600988", "depth": "2", "selected": false, "name": "\uc640\ud0c0\ub098\ubca0_\ucf04"}}, {"position": {"x": 770.5132427757893, "y": 637.4239897486897}, "data": {"id": "761652", "depth": "2", "selected": false, "name": "\uc694\uc2dc\uc624\uce74_\ud788\ub370\ud0c0\uce74"}}, {"position": {"x": 728.9686274214115, "y": 684.5471059286887}, "data": {"id": "761436", "depth": "2", "selected": false, "name": "\uc624\uac00\ud0c0_\ucf04"}}, {"position": {"x": 684.5471059286887, "y": 728.9686274214115}, "data": {"id": "764299", "depth": "2", "selected": false, "name": "\ub2c8\uc2dc\ub2e4_\ud1a0\uc2dc\uc720\ud0a4"}}, {"position": {"x": 637.4239897486898, "y": 770.5132427757893}, "data": {"id": "775124", "depth": "2", "selected": false, "name": "\uc9c4\ub098\uc774_\ud0c0\uce74\ub178\ub9ac"}}, {"position": {"x": 587.7852522924732, "y": 809.0169943749474}, "data": {"id": "739341", "depth": "2", "selected": false, "name": "\uc544\uce20\ubbf8_\ud0a4\uc694\uc2dc"}}, {"position": {"x": 535.8267949789965, "y": 844.3279255020151}, "data": {"id": "765226", "depth": "2", "selected": false, "name": "\ub098\uce74\uc774_\ud0a4\uc774\uce58"}}, {"position": {"x": 481.75367410171515, "y": 876.3066800438637}, "data": {"id": "724284", "depth": "2", "selected": false, "name": "\uc57c\ub9c8\uc790\ud0a4_\uce20\ud1a0\ubb34"}}, {"position": {"x": 425.77929156507264, "y": 904.8270524660196}, "data": {"id": "753790", "depth": "2", "selected": false, "name": "\ubaa8\ud1a0\ud0a4_\ub9c8\uc0ac\ud788\ub85c"}}, {"position": {"x": 368.12455268467806, "y": 929.7764858882514}, "data": {"id": "859143", "depth": "2", "selected": false, "name": "\ubbf8\uc988\ud0c0\ub2c8_\uc720\ud0c0\uce74"}}]}, "data": {"__Annotations": [], "name": "ko-wiki-pageNetwork", "selected": true, "shared_name": "ko-wiki-pageNetwork"}}