{"elements": {"edges": [{"data": {"id": "829923-829523", "ranking": 1, "width": 21, "interaction": "cw", "selected": false, "target": "829523", "source": "829923", "similarity": 0.5075048376712187}}, {"data": {"id": "829923-828599", "ranking": 2, "width": 1, "interaction": "cw", "selected": false, "target": "828599", "source": "829923", "similarity": 0.004353439830384648}}, {"data": {"id": "829523-829527", "ranking": 1, "width": 25, "interaction": "cw", "selected": false, "target": "829527", "source": "829523", "similarity": 0.608872840824161}}, {"data": {"id": "829523-829923", "ranking": 2, "width": 21, "interaction": "cw", "selected": false, "target": "829923", "source": "829523", "similarity": 0.5075048376712187}}, {"data": {"id": "828599-760184", "ranking": 1, "width": 11, "interaction": "cw", "selected": false, "target": "760184", "source": "828599", "similarity": 0.26573725921677166}}, {"data": {"id": "828599-3424", "ranking": 2, "width": 9, "interaction": "cw", "selected": false, "target": "3424", "source": "828599", "similarity": 0.2199810260773671}}, {"data": {"id": "828599-771199", "ranking": 3, "width": 9, "interaction": "cw", "selected": false, "target": "771199", "source": "828599", "similarity": 0.21841820286335814}}, {"data": {"id": "828599-139722", "ranking": 4, "width": 9, "interaction": "cw", "selected": false, "target": "139722", "source": "828599", "similarity": 0.21800839647963802}}, {"data": {"id": "828599-34596", "ranking": 5, "width": 9, "interaction": "cw", "selected": false, "target": "34596", "source": "828599", "similarity": 0.2060480884443803}}, {"data": {"id": "828599-1069500", "ranking": 6, "width": 9, "interaction": "cw", "selected": false, "target": "1069500", "source": "828599", "similarity": 0.20284942981612278}}, {"data": {"id": "828599-1069503", "ranking": 7, "width": 7, "interaction": "cw", "selected": false, "target": "1069503", "source": "828599", "similarity": 0.17336259951648747}}, {"data": {"id": "828599-139742", "ranking": 8, "width": 7, "interaction": "cw", "selected": false, "target": "139742", "source": "828599", "similarity": 0.17236371943079623}}, {"data": {"id": "828599-828526", "ranking": 9, "width": 7, "interaction": "cw", "selected": false, "target": "828526", "source": "828599", "similarity": 0.17072063336421833}}, {"data": {"id": "828599-760798", "ranking": 10, "width": 6, "interaction": "cw", "selected": false, "target": "760798", "source": "828599", "similarity": 0.12686481060446825}}], "nodes": [{"position": {"x": 0, "y": 0}, "data": {"id": "829923", "depth": "0", "selected": false, "name": "\uc800\uc6b0\ubcf4\ud654"}}, {"position": {"x": 100.0, "y": 0.0}, "data": {"id": "829523", "depth": "1", "selected": false, "name": "\uc7a5\uc708\ucd28"}}, {"position": {"x": 80.90169943749474, "y": 58.778525229247315}, "data": {"id": "828599", "depth": "1", "selected": false, "name": "\uc800\uc6b0\ucc3d"}}, {"position": {"x": 1000.0, "y": 0.0}, "data": {"id": "829527", "depth": "2", "selected": false, "name": "\uc7a5\uce6d\ub9ac"}}, {"position": {"x": 998.0267284282716, "y": 62.79051952931337}, "data": {"id": "829923", "depth": "2", "selected": false, "name": "\uc800\uc6b0\ubcf4\ud654"}}, {"position": {"x": 809.0169943749474, "y": 587.7852522924732}, "data": {"id": "760184", "depth": "2", "selected": false, "name": "\uc7a5\ub354\uc7a5"}}, {"position": {"x": 770.5132427757893, "y": 637.4239897486897}, "data": {"id": "3424", "depth": "2", "selected": false, "name": "\ub465\uc820\ud654"}}, {"position": {"x": 728.9686274214115, "y": 684.5471059286887}, "data": {"id": "771199", "depth": "2", "selected": false, "name": "\uc7a5\uac00\uc624\ub9ac"}}, {"position": {"x": 684.5471059286887, "y": 728.9686274214115}, "data": {"id": "139722", "depth": "2", "selected": false, "name": "\uc2dc\uc9c4\ud551"}}, {"position": {"x": 637.4239897486898, "y": 770.5132427757893}, "data": {"id": "34596", "depth": "2", "selected": false, "name": "\ud6c4\uc9c4\ud0c0\uc624"}}, {"position": {"x": 587.7852522924732, "y": 809.0169943749474}, "data": {"id": "1069500", "depth": "2", "selected": false, "name": "\ucc9c\ucc3d\uc988"}}, {"position": {"x": 535.8267949789965, "y": 844.3279255020151}, "data": {"id": "1069503", "depth": "2", "selected": false, "name": "\uc60c\uc954\uce58"}}, {"position": {"x": 481.75367410171515, "y": 876.3066800438637}, "data": {"id": "139742", "depth": "2", "selected": false, "name": "\ub9ac\ucee4\ucc3d"}}, {"position": {"x": 425.77929156507264, "y": 904.8270524660196}, "data": {"id": "828526", "depth": "2", "selected": false, "name": "\ud6c4\ucd98\ud654"}}, {"position": {"x": 368.12455268467806, "y": 929.7764858882514}, "data": {"id": "760798", "depth": "2", "selected": false, "name": "\ub958\uc60c\ub465"}}]}, "data": {"__Annotations": [], "name": "ko-wiki-pageNetwork", "selected": true, "shared_name": "ko-wiki-pageNetwork"}}