{"elements": {"edges": [{"data": {"id": "555689-41982", "ranking": 1, "width": 5, "interaction": "cw", "selected": false, "target": "41982", "source": "555689", "similarity": 0.10075337157330215}}, {"data": {"id": "41982-176956", "ranking": 1, "width": 21, "interaction": "cw", "selected": false, "target": "176956", "source": "41982", "similarity": 0.510644505197024}}, {"data": {"id": "41982-801422", "ranking": 2, "width": 10, "interaction": "cw", "selected": false, "target": "801422", "source": "41982", "similarity": 0.24435238336632517}}, {"data": {"id": "41982-555689", "ranking": 3, "width": 5, "interaction": "cw", "selected": false, "target": "555689", "source": "41982", "similarity": 0.10075337157330215}}], "nodes": [{"position": {"x": 0, "y": 0}, "data": {"id": "555689", "depth": "0", "selected": false, "name": "\ubc30\uc774\ub1cc_\ub9b0\ub098"}}, {"position": {"x": 100.0, "y": 0.0}, "data": {"id": "41982", "depth": "1", "selected": false, "name": "\uc5d0\ub9ac\ud788_\ub9c8\ub9ac\uc544_\ub808\ub9c8\ub974\ud06c"}}, {"position": {"x": 1000.0, "y": 0.0}, "data": {"id": "176956", "depth": "2", "selected": false, "name": "\ub77c\uc774\ub108_\ub9c8\ub9ac\uc544_\ub9b4\ucf00"}}, {"position": {"x": 998.0267284282716, "y": 62.79051952931337}, "data": {"id": "801422", "depth": "2", "selected": false, "name": "\ud3f4\ub808\ud2b8_\uace0\ub2e4\ub4dc"}}, {"position": {"x": 992.1147013144779, "y": 125.33323356430427}, "data": {"id": "555689", "depth": "2", "selected": false, "name": "\ubc30\uc774\ub1cc_\ub9b0\ub098"}}]}, "data": {"__Annotations": [], "name": "ko-wiki-pageNetwork", "selected": true, "shared_name": "ko-wiki-pageNetwork"}}