{"elements": {"edges": [{"data": {"id": "494246-411744", "ranking": 1, "width": 12, "interaction": "cw", "selected": false, "target": "411744", "source": "494246", "similarity": 0.2969127577798035}}, {"data": {"id": "494246-134823", "ranking": 2, "width": 4, "interaction": "cw", "selected": false, "target": "134823", "source": "494246", "similarity": 0.08985416389081988}}, {"data": {"id": "494246-69671", "ranking": 3, "width": 3, "interaction": "cw", "selected": false, "target": "69671", "source": "494246", "similarity": 0.06270244485014734}}, {"data": {"id": "411744-236956", "ranking": 1, "width": 15, "interaction": "cw", "selected": false, "target": "236956", "source": "411744", "similarity": 0.3678341890632762}}, {"data": {"id": "411744-494246", "ranking": 2, "width": 12, "interaction": "cw", "selected": false, "target": "494246", "source": "411744", "similarity": 0.2969127577798035}}, {"data": {"id": "411744-1143177", "ranking": 3, "width": 5, "interaction": "cw", "selected": false, "target": "1143177", "source": "411744", "similarity": 0.11494962549169252}}, {"data": {"id": "134823-750201", "ranking": 1, "width": 9, "interaction": "cw", "selected": false, "target": "750201", "source": "134823", "similarity": 0.20832644114458193}}, {"data": {"id": "134823-74295", "ranking": 2, "width": 6, "interaction": "cw", "selected": false, "target": "74295", "source": "134823", "similarity": 0.13920812079333642}}, {"data": {"id": "134823-334110", "ranking": 3, "width": 6, "interaction": "cw", "selected": false, "target": "334110", "source": "134823", "similarity": 0.12760051265183042}}, {"data": {"id": "134823-494246", "ranking": 4, "width": 4, "interaction": "cw", "selected": false, "target": "494246", "source": "134823", "similarity": 0.08985416389081988}}, {"data": {"id": "134823-902240", "ranking": 5, "width": 3, "interaction": "cw", "selected": false, "target": "902240", "source": "134823", "similarity": 0.06693982562267686}}, {"data": {"id": "134823-1228356", "ranking": 6, "width": 2, "interaction": "cw", "selected": false, "target": "1228356", "source": "134823", "similarity": 0.026075789151943352}}, {"data": {"id": "69671-174476", "ranking": 1, "width": 31, "interaction": "cw", "selected": false, "target": "174476", "source": "69671", "similarity": 0.7645731973925495}}, {"data": {"id": "69671-341683", "ranking": 2, "width": 12, "interaction": "cw", "selected": false, "target": "341683", "source": "69671", "similarity": 0.295488625214491}}, {"data": {"id": "69671-176396", "ranking": 3, "width": 12, "interaction": "cw", "selected": false, "target": "176396", "source": "69671", "similarity": 0.2915190847784533}}, {"data": {"id": "69671-112782", "ranking": 4, "width": 12, "interaction": "cw", "selected": false, "target": "112782", "source": "69671", "similarity": 0.28910788107776325}}, {"data": {"id": "69671-288599", "ranking": 5, "width": 12, "interaction": "cw", "selected": false, "target": "288599", "source": "69671", "similarity": 0.2860590183575391}}, {"data": {"id": "69671-256345", "ranking": 6, "width": 12, "interaction": "cw", "selected": false, "target": "256345", "source": "69671", "similarity": 0.28205694735027015}}, {"data": {"id": "69671-375876", "ranking": 7, "width": 12, "interaction": "cw", "selected": false, "target": "375876", "source": "69671", "similarity": 0.27903678253053094}}, {"data": {"id": "69671-118524", "ranking": 8, "width": 11, "interaction": "cw", "selected": false, "target": "118524", "source": "69671", "similarity": 0.2697285729263218}}, {"data": {"id": "69671-96924", "ranking": 9, "width": 11, "interaction": "cw", "selected": false, "target": "96924", "source": "69671", "similarity": 0.2695330289454445}}, {"data": {"id": "69671-268997", "ranking": 10, "width": 11, "interaction": "cw", "selected": false, "target": "268997", "source": "69671", "similarity": 0.25603248216387636}}], "nodes": [{"position": {"x": 0, "y": 0}, "data": {"id": "494246", "depth": "0", "selected": false, "name": "\ud558\uccad\uc77c"}}, {"position": {"x": 100.0, "y": 0.0}, "data": {"id": "411744", "depth": "1", "selected": false, "name": "\uc11c\uc218\ub0a8"}}, {"position": {"x": 80.90169943749474, "y": 58.778525229247315}, "data": {"id": "134823", "depth": "1", "selected": false, "name": "\ubc30\ud638"}}, {"position": {"x": 30.901699437494745, "y": 95.10565162951535}, "data": {"id": "69671", "depth": "1", "selected": false, "name": "\uc774\uc8fc\uc77c"}}, {"position": {"x": 1000.0, "y": 0.0}, "data": {"id": "236956", "depth": "2", "selected": false, "name": "\uc124\uc6b4\ub3c4"}}, {"position": {"x": 998.0267284282716, "y": 62.79051952931337}, "data": {"id": "494246", "depth": "2", "selected": false, "name": "\ud558\uccad\uc77c"}}, {"position": {"x": 992.1147013144779, "y": 125.33323356430427}, "data": {"id": "1143177", "depth": "2", "selected": false, "name": "\ud589\ud06c_\uc2a4\ub178"}}, {"position": {"x": 809.0169943749474, "y": 587.7852522924732}, "data": {"id": "750201", "depth": "2", "selected": false, "name": "\ucc28\uc911\ub77d"}}, {"position": {"x": 770.5132427757893, "y": 637.4239897486897}, "data": {"id": "74295", "depth": "2", "selected": false, "name": "\uc5d8\ube44\uc2a4_\ud504\ub808\uc2ac\ub9ac"}}, {"position": {"x": 728.9686274214115, "y": 684.5471059286887}, "data": {"id": "334110", "depth": "2", "selected": false, "name": "\uc815\ub3d9\ud558"}}, {"position": {"x": 684.5471059286887, "y": 728.9686274214115}, "data": {"id": "494246", "depth": "2", "selected": false, "name": "\ud558\uccad\uc77c"}}, {"position": {"x": 637.4239897486898, "y": 770.5132427757893}, "data": {"id": "902240", "depth": "2", "selected": false, "name": "\uc0b0\ub4e4"}}, {"position": {"x": 587.7852522924732, "y": 809.0169943749474}, "data": {"id": "1228356", "depth": "2", "selected": false, "name": "\uc774\ud55c\ud544"}}, {"position": {"x": 309.01699437494744, "y": 951.0565162951535}, "data": {"id": "174476", "depth": "2", "selected": false, "name": "\uc774\uc8fc\uc77c_(\uad70\uc778)"}}, {"position": {"x": 248.68988716485475, "y": 968.5831611286311}, "data": {"id": "341683", "depth": "2", "selected": false, "name": "\uc2ec\ud604\uc12d"}}, {"position": {"x": 187.38131458572474, "y": 982.2872507286886}, "data": {"id": "176396", "depth": "2", "selected": false, "name": "\uc774\uc218\uadfc_(\ud76c\uadf9\uc778)"}}, {"position": {"x": 125.33323356430427, "y": 992.1147013144779}, "data": {"id": "112782", "depth": "2", "selected": false, "name": "\uc2e0\ub3d9\uc5fd_(\ud76c\uadf9\uc778)"}}, {"position": {"x": 62.79051952931353, "y": 998.0267284282716}, "data": {"id": "288599", "depth": "2", "selected": false, "name": "\uae40\uc6a9\ub9cc_(\ud76c\uadf9\uc778)"}}, {"position": {"x": 6.123233995736766e-14, "y": 1000.0}, "data": {"id": "256345", "depth": "2", "selected": false, "name": "\uae40\ubcd1\ub9cc"}}, {"position": {"x": -62.7905195293134, "y": 998.0267284282716}, "data": {"id": "375876", "depth": "2", "selected": false, "name": "\uc815\uc885\ucca0"}}, {"position": {"x": -125.33323356430436, "y": 992.1147013144778}, "data": {"id": "118524", "depth": "2", "selected": false, "name": "\uae40\uc815\uc2dd_(\ud76c\uadf9\uc778)"}}, {"position": {"x": -187.3813145857246, "y": 982.2872507286887}, "data": {"id": "96924", "depth": "2", "selected": false, "name": "\uc720\uc7ac\uc11d"}}, {"position": {"x": -248.68988716485464, "y": 968.5831611286312}, "data": {"id": "268997", "depth": "2", "selected": false, "name": "\ubc15\uc131\ud638_(\ud76c\uadf9\uc778)"}}]}, "data": {"__Annotations": [], "name": "ko-wiki-pageNetwork", "selected": true, "shared_name": "ko-wiki-pageNetwork"}}