{"elements": {"edges": [{"data": {"similarity": 0.25658601924498076, "id": "881187-138687", "source": "881187", "width": 11, "interaction": "cw", "selected": false, "ranking": 1, "target": "138687"}}, {"data": {"similarity": 0.25172336350327373, "id": "881187-337698", "source": "881187", "width": 11, "interaction": "cw", "selected": false, "ranking": 2, "target": "337698"}}, {"data": {"similarity": 0.2506203564451813, "id": "881187-11483", "source": "881187", "width": 11, "interaction": "cw", "selected": false, "ranking": 3, "target": "11483"}}, {"data": {"similarity": 0.2273302410446364, "id": "881187-338125", "source": "881187", "width": 10, "interaction": "cw", "selected": false, "ranking": 4, "target": "338125"}}, {"data": {"similarity": 0.22485383558914285, "id": "881187-139742", "source": "881187", "width": 9, "interaction": "cw", "selected": false, "ranking": 5, "target": "139742"}}, {"data": {"similarity": 0.22335199993868946, "id": "881187-163964", "source": "881187", "width": 9, "interaction": "cw", "selected": false, "ranking": 6, "target": "163964"}}, {"data": {"similarity": 0.21889581116406184, "id": "881187-74769", "source": "881187", "width": 9, "interaction": "cw", "selected": false, "ranking": 7, "target": "74769"}}, {"data": {"similarity": 0.2137414167356297, "id": "881187-165332", "source": "881187", "width": 9, "interaction": "cw", "selected": false, "ranking": 8, "target": "165332"}}, {"data": {"similarity": 0.21011088712255732, "id": "881187-882608", "source": "881187", "width": 9, "interaction": "cw", "selected": false, "ranking": 9, "target": "882608"}}, {"data": {"similarity": 0.20952846979100107, "id": "881187-890741", "source": "881187", "width": 9, "interaction": "cw", "selected": false, "ranking": 10, "target": "890741"}}, {"data": {"similarity": 0.4954619976631352, "id": "138687-74769", "source": "138687", "width": 20, "interaction": "cw", "selected": false, "ranking": 1, "target": "74769"}}, {"data": {"similarity": 0.44971610919098426, "id": "138687-163950", "source": "138687", "width": 18, "interaction": "cw", "selected": false, "ranking": 2, "target": "163950"}}, {"data": {"similarity": 0.4458524645895403, "id": "138687-42418", "source": "138687", "width": 18, "interaction": "cw", "selected": false, "ranking": 3, "target": "42418"}}, {"data": {"similarity": 0.4441553008618951, "id": "138687-11483", "source": "138687", "width": 18, "interaction": "cw", "selected": false, "ranking": 4, "target": "11483"}}, {"data": {"similarity": 0.4138358896785981, "id": "138687-2577", "source": "138687", "width": 17, "interaction": "cw", "selected": false, "ranking": 5, "target": "2577"}}, {"data": {"similarity": 0.4015856735968529, "id": "138687-41371", "source": "138687", "width": 17, "interaction": "cw", "selected": false, "ranking": 6, "target": "41371"}}, {"data": {"similarity": 0.38482590503754305, "id": "138687-138933", "source": "138687", "width": 16, "interaction": "cw", "selected": false, "ranking": 7, "target": "138933"}}, {"data": {"similarity": 0.3840165728331919, "id": "138687-163794", "source": "138687", "width": 16, "interaction": "cw", "selected": false, "ranking": 8, "target": "163794"}}, {"data": {"similarity": 0.371538703117608, "id": "138687-139722", "source": "138687", "width": 15, "interaction": "cw", "selected": false, "ranking": 9, "target": "139722"}}, {"data": {"similarity": 0.3687186996095834, "id": "138687-139742", "source": "138687", "width": 15, "interaction": "cw", "selected": false, "ranking": 10, "target": "139742"}}, {"data": {"similarity": 0.4923810304022121, "id": "337698-338414", "source": "337698", "width": 20, "interaction": "cw", "selected": false, "ranking": 1, "target": "338414"}}, {"data": {"similarity": 0.4544041697834771, "id": "337698-338125", "source": "337698", "width": 19, "interaction": "cw", "selected": false, "ranking": 2, "target": "338125"}}, {"data": {"similarity": 0.4176584502988279, "id": "337698-164902", "source": "337698", "width": 17, "interaction": "cw", "selected": false, "ranking": 3, "target": "164902"}}, {"data": {"similarity": 0.41564437637724994, "id": "337698-138933", "source": "337698", "width": 17, "interaction": "cw", "selected": false, "ranking": 4, "target": "138933"}}, {"data": {"similarity": 0.3666202656361963, "id": "337698-178532", "source": "337698", "width": 15, "interaction": "cw", "selected": false, "ranking": 5, "target": "178532"}}, {"data": {"similarity": 0.358629936255937, "id": "337698-163794", "source": "337698", "width": 15, "interaction": "cw", "selected": false, "ranking": 6, "target": "163794"}}, {"data": {"similarity": 0.354614093923912, "id": "337698-42418", "source": "337698", "width": 15, "interaction": "cw", "selected": false, "ranking": 7, "target": "42418"}}, {"data": {"similarity": 0.3468947100981679, "id": "337698-164095", "source": "337698", "width": 14, "interaction": "cw", "selected": false, "ranking": 8, "target": "164095"}}, {"data": {"similarity": 0.34542011946462436, "id": "337698-11483", "source": "337698", "width": 14, "interaction": "cw", "selected": false, "ranking": 9, "target": "11483"}}, {"data": {"similarity": 0.3415991112176996, "id": "337698-138687", "source": "337698", "width": 14, "interaction": "cw", "selected": false, "ranking": 10, "target": "138687"}}, {"data": {"similarity": 0.5324124274612912, "id": "11483-2577", "source": "11483", "width": 22, "interaction": "cw", "selected": false, "ranking": 1, "target": "2577"}}, {"data": {"similarity": 0.49376515835724094, "id": "11483-166250", "source": "11483", "width": 20, "interaction": "cw", "selected": false, "ranking": 2, "target": "166250"}}, {"data": {"similarity": 0.4441553008618951, "id": "11483-138687", "source": "11483", "width": 18, "interaction": "cw", "selected": false, "ranking": 3, "target": "138687"}}, {"data": {"similarity": 0.43349568371688596, "id": "11483-34596", "source": "11483", "width": 18, "interaction": "cw", "selected": false, "ranking": 4, "target": "34596"}}, {"data": {"similarity": 0.4242179394517789, "id": "11483-163794", "source": "11483", "width": 17, "interaction": "cw", "selected": false, "ranking": 5, "target": "163794"}}, {"data": {"similarity": 0.41537858830907626, "id": "11483-139722", "source": "11483", "width": 17, "interaction": "cw", "selected": false, "ranking": 6, "target": "139722"}}, {"data": {"similarity": 0.4133309899367698, "id": "11483-138933", "source": "11483", "width": 17, "interaction": "cw", "selected": false, "ranking": 7, "target": "138933"}}, {"data": {"similarity": 0.41247536631075987, "id": "11483-42418", "source": "11483", "width": 17, "interaction": "cw", "selected": false, "ranking": 8, "target": "42418"}}, {"data": {"similarity": 0.40611056644928833, "id": "11483-9956", "source": "11483", "width": 17, "interaction": "cw", "selected": false, "ranking": 9, "target": "9956"}}, {"data": {"similarity": 0.4016055608658791, "id": "11483-138204", "source": "11483", "width": 17, "interaction": "cw", "selected": false, "ranking": 10, "target": "138204"}}, {"data": {"similarity": 0.576523087657924, "id": "338125-338414", "source": "338125", "width": 24, "interaction": "cw", "selected": false, "ranking": 1, "target": "338414"}}, {"data": {"similarity": 0.4731075362353876, "id": "338125-164902", "source": "338125", "width": 19, "interaction": "cw", "selected": false, "ranking": 2, "target": "164902"}}, {"data": {"similarity": 0.4544041697834771, "id": "338125-337698", "source": "338125", "width": 19, "interaction": "cw", "selected": false, "ranking": 3, "target": "337698"}}, {"data": {"similarity": 0.35953781142451696, "id": "338125-163794", "source": "338125", "width": 15, "interaction": "cw", "selected": false, "ranking": 4, "target": "163794"}}, {"data": {"similarity": 0.35607869372197637, "id": "338125-138687", "source": "338125", "width": 15, "interaction": "cw", "selected": false, "ranking": 5, "target": "138687"}}, {"data": {"similarity": 0.35033194875267376, "id": "338125-178532", "source": "338125", "width": 15, "interaction": "cw", "selected": false, "ranking": 6, "target": "178532"}}, {"data": {"similarity": 0.33795019717589514, "id": "338125-167374", "source": "338125", "width": 14, "interaction": "cw", "selected": false, "ranking": 7, "target": "167374"}}, {"data": {"similarity": 0.32681024180619545, "id": "338125-42418", "source": "338125", "width": 14, "interaction": "cw", "selected": false, "ranking": 8, "target": "42418"}}, {"data": {"similarity": 0.31783526618881563, "id": "338125-760184", "source": "338125", "width": 13, "interaction": "cw", "selected": false, "ranking": 9, "target": "760184"}}, {"data": {"similarity": 0.3160344625761154, "id": "338125-165332", "source": "338125", "width": 13, "interaction": "cw", "selected": false, "ranking": 10, "target": "165332"}}, {"data": {"similarity": 0.3687186996095834, "id": "139742-138687", "source": "139742", "width": 15, "interaction": "cw", "selected": false, "ranking": 1, "target": "138687"}}, {"data": {"similarity": 0.306983096453485, "id": "139742-771199", "source": "139742", "width": 13, "interaction": "cw", "selected": false, "ranking": 2, "target": "771199"}}, {"data": {"similarity": 0.3049096293154958, "id": "139742-2577", "source": "139742", "width": 13, "interaction": "cw", "selected": false, "ranking": 3, "target": "2577"}}, {"data": {"similarity": 0.30125356870152975, "id": "139742-11483", "source": "139742", "width": 13, "interaction": "cw", "selected": false, "ranking": 4, "target": "11483"}}, {"data": {"similarity": 0.3008183654710734, "id": "139742-74769", "source": "139742", "width": 13, "interaction": "cw", "selected": false, "ranking": 5, "target": "74769"}}, {"data": {"similarity": 0.2975235797337596, "id": "139742-41371", "source": "139742", "width": 12, "interaction": "cw", "selected": false, "ranking": 6, "target": "41371"}}, {"data": {"similarity": 0.28752451243046473, "id": "139742-139722", "source": "139742", "width": 12, "interaction": "cw", "selected": false, "ranking": 7, "target": "139722"}}, {"data": {"similarity": 0.27686732846213635, "id": "139742-101637", "source": "139742", "width": 12, "interaction": "cw", "selected": false, "ranking": 8, "target": "101637"}}, {"data": {"similarity": 0.2741608394604619, "id": "139742-42418", "source": "139742", "width": 11, "interaction": "cw", "selected": false, "ranking": 9, "target": "42418"}}, {"data": {"similarity": 0.26684821898762207, "id": "139742-34596", "source": "139742", "width": 11, "interaction": "cw", "selected": false, "ranking": 10, "target": "34596"}}, {"data": {"similarity": 0.36043021557895966, "id": "163964-163794", "source": "163964", "width": 15, "interaction": "cw", "selected": false, "ranking": 1, "target": "163794"}}, {"data": {"similarity": 0.3445494746702581, "id": "163964-164902", "source": "163964", "width": 14, "interaction": "cw", "selected": false, "ranking": 2, "target": "164902"}}, {"data": {"similarity": 0.31664343804825157, "id": "163964-149475", "source": "163964", "width": 13, "interaction": "cw", "selected": false, "ranking": 3, "target": "149475"}}, {"data": {"similarity": 0.30675553437852443, "id": "163964-338125", "source": "163964", "width": 13, "interaction": "cw", "selected": false, "ranking": 4, "target": "338125"}}, {"data": {"similarity": 0.3004136232672263, "id": "163964-165332", "source": "163964", "width": 13, "interaction": "cw", "selected": false, "ranking": 5, "target": "165332"}}, {"data": {"similarity": 0.3003269763842977, "id": "163964-137872", "source": "163964", "width": 13, "interaction": "cw", "selected": false, "ranking": 6, "target": "137872"}}, {"data": {"similarity": 0.29018866277853556, "id": "163964-337698", "source": "163964", "width": 12, "interaction": "cw", "selected": false, "ranking": 7, "target": "337698"}}, {"data": {"similarity": 0.2870390049538797, "id": "163964-138933", "source": "163964", "width": 12, "interaction": "cw", "selected": false, "ranking": 8, "target": "138933"}}, {"data": {"similarity": 0.28647804190890375, "id": "163964-42418", "source": "163964", "width": 12, "interaction": "cw", "selected": false, "ranking": 9, "target": "42418"}}, {"data": {"similarity": 0.2820307655367725, "id": "163964-101637", "source": "163964", "width": 12, "interaction": "cw", "selected": false, "ranking": 10, "target": "101637"}}, {"data": {"similarity": 0.4954619976631352, "id": "74769-138687", "source": "74769", "width": 20, "interaction": "cw", "selected": false, "ranking": 1, "target": "138687"}}, {"data": {"similarity": 0.4405453047949902, "id": "74769-41371", "source": "74769", "width": 18, "interaction": "cw", "selected": false, "ranking": 2, "target": "41371"}}, {"data": {"similarity": 0.3898011156533286, "id": "74769-42418", "source": "74769", "width": 16, "interaction": "cw", "selected": false, "ranking": 3, "target": "42418"}}, {"data": {"similarity": 0.3777344061468399, "id": "74769-2577", "source": "74769", "width": 16, "interaction": "cw", "selected": false, "ranking": 4, "target": "2577"}}, {"data": {"similarity": 0.3755804414098459, "id": "74769-34596", "source": "74769", "width": 16, "interaction": "cw", "selected": false, "ranking": 5, "target": "34596"}}, {"data": {"similarity": 0.37129272585347545, "id": "74769-139722", "source": "74769", "width": 15, "interaction": "cw", "selected": false, "ranking": 6, "target": "139722"}}, {"data": {"similarity": 0.3572484970168191, "id": "74769-11483", "source": "74769", "width": 15, "interaction": "cw", "selected": false, "ranking": 7, "target": "11483"}}, {"data": {"similarity": 0.31867620275163, "id": "74769-163794", "source": "74769", "width": 13, "interaction": "cw", "selected": false, "ranking": 8, "target": "163794"}}, {"data": {"similarity": 0.3008183654710734, "id": "74769-139742", "source": "74769", "width": 13, "interaction": "cw", "selected": false, "ranking": 9, "target": "139742"}}, {"data": {"similarity": 0.27639563886241114, "id": "74769-138204", "source": "74769", "width": 12, "interaction": "cw", "selected": false, "ranking": 10, "target": "138204"}}, {"data": {"similarity": 0.522109474993078, "id": "165332-166032", "source": "165332", "width": 21, "interaction": "cw", "selected": false, "ranking": 1, "target": "166032"}}, {"data": {"similarity": 0.47110221156720056, "id": "165332-42418", "source": "165332", "width": 19, "interaction": "cw", "selected": false, "ranking": 2, "target": "42418"}}, {"data": {"similarity": 0.43732330646025264, "id": "165332-164902", "source": "165332", "width": 18, "interaction": "cw", "selected": false, "ranking": 3, "target": "164902"}}, {"data": {"similarity": 0.4334226730679933, "id": "165332-168460", "source": "165332", "width": 18, "interaction": "cw", "selected": false, "ranking": 4, "target": "168460"}}, {"data": {"similarity": 0.4315763040084013, "id": "165332-167374", "source": "165332", "width": 18, "interaction": "cw", "selected": false, "ranking": 5, "target": "167374"}}, {"data": {"similarity": 0.42324610115667366, "id": "165332-164095", "source": "165332", "width": 17, "interaction": "cw", "selected": false, "ranking": 6, "target": "164095"}}, {"data": {"similarity": 0.4065848370556432, "id": "165332-163794", "source": "165332", "width": 17, "interaction": "cw", "selected": false, "ranking": 7, "target": "163794"}}, {"data": {"similarity": 0.392669647243572, "id": "165332-81426", "source": "165332", "width": 16, "interaction": "cw", "selected": false, "ranking": 8, "target": "81426"}}, {"data": {"similarity": 0.38315947780063403, "id": "165332-468", "source": "165332", "width": 16, "interaction": "cw", "selected": false, "ranking": 9, "target": "468"}}, {"data": {"similarity": 0.38196500139352374, "id": "165332-138933", "source": "165332", "width": 16, "interaction": "cw", "selected": false, "ranking": 10, "target": "138933"}}, {"data": {"similarity": 0.3559017558037137, "id": "882608-41371", "source": "882608", "width": 15, "interaction": "cw", "selected": false, "ranking": 1, "target": "41371"}}, {"data": {"similarity": 0.3427050994885823, "id": "882608-42418", "source": "882608", "width": 14, "interaction": "cw", "selected": false, "ranking": 2, "target": "42418"}}, {"data": {"similarity": 0.33309114115137023, "id": "882608-139722", "source": "882608", "width": 14, "interaction": "cw", "selected": false, "ranking": 3, "target": "139722"}}, {"data": {"similarity": 0.32934779473931625, "id": "882608-163794", "source": "882608", "width": 14, "interaction": "cw", "selected": false, "ranking": 4, "target": "163794"}}, {"data": {"similarity": 0.30886142939527095, "id": "882608-2577", "source": "882608", "width": 13, "interaction": "cw", "selected": false, "ranking": 5, "target": "2577"}}, {"data": {"similarity": 0.30311609228416525, "id": "882608-468", "source": "882608", "width": 13, "interaction": "cw", "selected": false, "ranking": 6, "target": "468"}}, {"data": {"similarity": 0.30022842094141267, "id": "882608-138941", "source": "882608", "width": 13, "interaction": "cw", "selected": false, "ranking": 7, "target": "138941"}}, {"data": {"similarity": 0.2942680971755954, "id": "882608-138204", "source": "882608", "width": 12, "interaction": "cw", "selected": false, "ranking": 8, "target": "138204"}}, {"data": {"similarity": 0.28886207628650096, "id": "882608-760184", "source": "882608", "width": 12, "interaction": "cw", "selected": false, "ranking": 9, "target": "760184"}}, {"data": {"similarity": 0.2864006230578953, "id": "882608-101637", "source": "882608", "width": 12, "interaction": "cw", "selected": false, "ranking": 10, "target": "101637"}}, {"data": {"similarity": 0.2185415013465637, "id": "890741-882572", "source": "890741", "width": 9, "interaction": "cw", "selected": false, "ranking": 1, "target": "882572"}}, {"data": {"similarity": 0.2141355947295509, "id": "890741-890728", "source": "890741", "width": 9, "interaction": "cw", "selected": false, "ranking": 2, "target": "890728"}}, {"data": {"similarity": 0.20952846979100107, "id": "890741-881187", "source": "890741", "width": 9, "interaction": "cw", "selected": false, "ranking": 3, "target": "881187"}}, {"data": {"similarity": 0.2052838239418861, "id": "890741-875149", "source": "890741", "width": 9, "interaction": "cw", "selected": false, "ranking": 4, "target": "875149"}}, {"data": {"similarity": 0.2003808464377014, "id": "890741-882608", "source": "890741", "width": 9, "interaction": "cw", "selected": false, "ranking": 5, "target": "882608"}}, {"data": {"similarity": 0.20009281110864477, "id": "890741-167319", "source": "890741", "width": 9, "interaction": "cw", "selected": false, "ranking": 6, "target": "167319"}}, {"data": {"similarity": 0.18274587053666824, "id": "890741-163964", "source": "890741", "width": 8, "interaction": "cw", "selected": false, "ranking": 7, "target": "163964"}}, {"data": {"similarity": 0.1821918079867149, "id": "890741-882080", "source": "890741", "width": 8, "interaction": "cw", "selected": false, "ranking": 8, "target": "882080"}}, {"data": {"similarity": 0.1737220982487496, "id": "890741-164095", "source": "890741", "width": 7, "interaction": "cw", "selected": false, "ranking": 9, "target": "164095"}}, {"data": {"similarity": 0.17316699510567743, "id": "890741-393695", "source": "890741", "width": 7, "interaction": "cw", "selected": false, "ranking": 10, "target": "393695"}}], "nodes": [{"position": {"y": 0, "x": 0}, "data": {"depth": "0", "name": "\uc57c\uc624\uc774\ub9b0", "selected": false, "id": "881187"}}, {"position": {"y": 0.0, "x": 100.0}, "data": {"depth": "1", "name": "\ub9ac\ud391", "selected": false, "id": "138687"}}, {"position": {"y": 58.778525229247315, "x": 80.90169943749474}, "data": {"depth": "1", "name": "\uc655\ud6d9\uc6d0", "selected": false, "id": "337698"}}, {"position": {"y": 95.10565162951535, "x": 30.901699437494745}, "data": {"depth": "1", "name": "\uc790\uc624\ucbd4\uc591", "selected": false, "id": "11483"}}, {"position": {"y": 95.10565162951536, "x": -30.901699437494734}, "data": {"depth": "1", "name": "\uc7a5\ucd98\ucc28\uc624", "selected": false, "id": "338125"}}, {"position": {"y": 58.77852522924732, "x": -80.90169943749473}, "data": {"depth": "1", "name": "\ub9ac\ucee4\ucc3d", "selected": false, "id": "139742"}}, {"position": {"y": 1.2246467991473532e-14, "x": -100.0}, "data": {"depth": "1", "name": "\ub465\ube44\uc6b0", "selected": false, "id": "163964"}}, {"position": {"y": -58.7785252292473, "x": -80.90169943749474}, "data": {"depth": "1", "name": "\uc6d0\uc790\ubc14\uc624", "selected": false, "id": "74769"}}, {"position": {"y": -95.10565162951535, "x": -30.901699437494756}, "data": {"depth": "1", "name": "\ub9b0\ubc4c\uc624", "selected": false, "id": "165332"}}, {"position": {"y": -95.10565162951536, "x": 30.901699437494724}, "data": {"depth": "1", "name": "\ub9ac\ud478\ucd98", "selected": false, "id": "882608"}}, {"position": {"y": -58.778525229247336, "x": 80.90169943749473}, "data": {"depth": "1", "name": "\uc0f9\uc789", "selected": false, "id": "890741"}}, {"position": {"y": 0.0, "x": 1000.0}, "data": {"depth": "2", "name": "\uc6d0\uc790\ubc14\uc624", "selected": false, "id": "74769"}}, {"position": {"y": 62.79051952931337, "x": 998.0267284282716}, "data": {"depth": "2", "name": "\uc591\uc0c1\ucfe4", "selected": false, "id": "163950"}}, {"position": {"y": 125.33323356430427, "x": 992.1147013144779}, "data": {"depth": "2", "name": "\uc800\uc6b0\uc5b8\ub77c\uc774", "selected": false, "id": "42418"}}, {"position": {"y": 187.38131458572462, "x": 982.2872507286887}, "data": {"depth": "2", "name": "\uc790\uc624\ucbd4\uc591", "selected": false, "id": "11483"}}, {"position": {"y": 248.68988716485478, "x": 968.5831611286311}, "data": {"depth": "2", "name": "\uc7a5\uca4c\ubbfc", "selected": false, "id": "2577"}}, {"position": {"y": 309.0169943749474, "x": 951.0565162951535}, "data": {"depth": "2", "name": "\uc8fc\ub8fd\uc9c0", "selected": false, "id": "41371"}}, {"position": {"y": 368.12455268467795, "x": 929.7764858882515}, "data": {"depth": "2", "name": "\ud654\uad88\ud391", "selected": false, "id": "138933"}}, {"position": {"y": 425.7792915650727, "x": 904.8270524660195}, "data": {"depth": "2", "name": "\ub958\uc0ac\uc624\uce58", "selected": false, "id": "163794"}}, {"position": {"y": 481.7536741017153, "x": 876.3066800438636}, "data": {"depth": "2", "name": "\uc2dc\uc9c4\ud551", "selected": false, "id": "139722"}}, {"position": {"y": 535.8267949789966, "x": 844.3279255020151}, "data": {"depth": "2", "name": "\ub9ac\ucee4\ucc3d", "selected": false, "id": "139742"}}, {"position": {"y": 587.7852522924732, "x": 809.0169943749474}, "data": {"depth": "2", "name": "\uc57c\uc624\uc6d0\uc704\uc548", "selected": false, "id": "338414"}}, {"position": {"y": 637.4239897486897, "x": 770.5132427757893}, "data": {"depth": "2", "name": "\uc7a5\ucd98\ucc28\uc624", "selected": false, "id": "338125"}}, {"position": {"y": 684.5471059286887, "x": 728.9686274214115}, "data": {"depth": "2", "name": "\uc7a5\uce6d", "selected": false, "id": "164902"}}, {"position": {"y": 728.9686274214115, "x": 684.5471059286887}, "data": {"depth": "2", "name": "\ud654\uad88\ud391", "selected": false, "id": "138933"}}, {"position": {"y": 770.5132427757893, "x": 637.4239897486898}, "data": {"depth": "2", "name": "\ucde8\ucd94\ubc14\uc774", "selected": false, "id": "178532"}}, {"position": {"y": 809.0169943749474, "x": 587.7852522924732}, "data": {"depth": "2", "name": "\ub958\uc0ac\uc624\uce58", "selected": false, "id": "163794"}}, {"position": {"y": 844.3279255020151, "x": 535.8267949789965}, "data": {"depth": "2", "name": "\uc800\uc6b0\uc5b8\ub77c\uc774", "selected": false, "id": "42418"}}, {"position": {"y": 876.3066800438637, "x": 481.75367410171515}, "data": {"depth": "2", "name": "\uc8fc\ub354", "selected": false, "id": "164095"}}, {"position": {"y": 904.8270524660196, "x": 425.77929156507264}, "data": {"depth": "2", "name": "\uc790\uc624\ucbd4\uc591", "selected": false, "id": "11483"}}, {"position": {"y": 929.7764858882514, "x": 368.12455268467806}, "data": {"depth": "2", "name": "\ub9ac\ud391", "selected": false, "id": "138687"}}, {"position": {"y": 951.0565162951535, "x": 309.01699437494744}, "data": {"depth": "2", "name": "\uc7a5\uca4c\ubbfc", "selected": false, "id": "2577"}}, {"position": {"y": 968.5831611286311, "x": 248.68988716485475}, "data": {"depth": "2", "name": "\ud6c4\uc57c\uc624\ubc29", "selected": false, "id": "166250"}}, {"position": {"y": 982.2872507286886, "x": 187.38131458572474}, "data": {"depth": "2", "name": "\ub9ac\ud391", "selected": false, "id": "138687"}}, {"position": {"y": 992.1147013144779, "x": 125.33323356430427}, "data": {"depth": "2", "name": "\ud6c4\uc9c4\ud0c0\uc624", "selected": false, "id": "34596"}}, {"position": {"y": 998.0267284282716, "x": 62.79051952931353}, "data": {"depth": "2", "name": "\ub958\uc0ac\uc624\uce58", "selected": false, "id": "163794"}}, {"position": {"y": 1000.0, "x": 6.123233995736766e-14}, "data": {"depth": "2", "name": "\uc2dc\uc9c4\ud551", "selected": false, "id": "139722"}}, {"position": {"y": 998.0267284282716, "x": -62.7905195293134}, "data": {"depth": "2", "name": "\ud654\uad88\ud391", "selected": false, "id": "138933"}}, {"position": {"y": 992.1147013144778, "x": -125.33323356430436}, "data": {"depth": "2", "name": "\uc800\uc6b0\uc5b8\ub77c\uc774", "selected": false, "id": "42418"}}, {"position": {"y": 982.2872507286887, "x": -187.3813145857246}, "data": {"depth": "2", "name": "\ucc9c\ub450\uc288", "selected": false, "id": "9956"}}, {"position": {"y": 968.5831611286312, "x": -248.68988716485464}, "data": {"depth": "2", "name": "\uca61\uce6d\ud6d9", "selected": false, "id": "138204"}}, {"position": {"y": 951.0565162951536, "x": -309.01699437494733}, "data": {"depth": "2", "name": "\uc57c\uc624\uc6d0\uc704\uc548", "selected": false, "id": "338414"}}, {"position": {"y": 929.7764858882515, "x": -368.12455268467795}, "data": {"depth": "2", "name": "\uc7a5\uce6d", "selected": false, "id": "164902"}}, {"position": {"y": 904.8270524660195, "x": -425.7792915650727}, "data": {"depth": "2", "name": "\uc655\ud6d9\uc6d0", "selected": false, "id": "337698"}}, {"position": {"y": 876.3066800438637, "x": -481.75367410171503}, "data": {"depth": "2", "name": "\ub958\uc0ac\uc624\uce58", "selected": false, "id": "163794"}}, {"position": {"y": 844.3279255020152, "x": -535.8267949789964}, "data": {"depth": "2", "name": "\ub9ac\ud391", "selected": false, "id": "138687"}}, {"position": {"y": 809.0169943749474, "x": -587.785252292473}, "data": {"depth": "2", "name": "\ucde8\ucd94\ubc14\uc774", "selected": false, "id": "178532"}}, {"position": {"y": 770.5132427757893, "x": -637.4239897486898}, "data": {"depth": "2", "name": "\uc7a5\uad88\ud0c0\uc624", "selected": false, "id": "167374"}}, {"position": {"y": 728.9686274214115, "x": -684.5471059286888}, "data": {"depth": "2", "name": "\uc800\uc6b0\uc5b8\ub77c\uc774", "selected": false, "id": "42418"}}, {"position": {"y": 684.5471059286889, "x": -728.9686274214114}, "data": {"depth": "2", "name": "\uc7a5\ub354\uc7a5", "selected": false, "id": "760184"}}, {"position": {"y": 637.4239897486899, "x": -770.5132427757892}, "data": {"depth": "2", "name": "\ub9b0\ubc4c\uc624", "selected": false, "id": "165332"}}, {"position": {"y": 587.7852522924733, "x": -809.0169943749473}, "data": {"depth": "2", "name": "\ub9ac\ud391", "selected": false, "id": "138687"}}, {"position": {"y": 535.8267949789966, "x": -844.3279255020151}, "data": {"depth": "2", "name": "\uc7a5\uac00\uc624\ub9ac", "selected": false, "id": "771199"}}, {"position": {"y": 481.7536741017152, "x": -876.3066800438636}, "data": {"depth": "2", "name": "\uc7a5\uca4c\ubbfc", "selected": false, "id": "2577"}}, {"position": {"y": 425.77929156507287, "x": -904.8270524660194}, "data": {"depth": "2", "name": "\uc790\uc624\ucbd4\uc591", "selected": false, "id": "11483"}}, {"position": {"y": 368.1245526846781, "x": -929.7764858882514}, "data": {"depth": "2", "name": "\uc6d0\uc790\ubc14\uc624", "selected": false, "id": "74769"}}, {"position": {"y": 309.0169943749475, "x": -951.0565162951535}, "data": {"depth": "2", "name": "\uc8fc\ub8fd\uc9c0", "selected": false, "id": "41371"}}, {"position": {"y": 248.6898871648548, "x": -968.5831611286311}, "data": {"depth": "2", "name": "\uc2dc\uc9c4\ud551", "selected": false, "id": "139722"}}, {"position": {"y": 187.38131458572457, "x": -982.2872507286887}, "data": {"depth": "2", "name": "\ud669\uc950", "selected": false, "id": "101637"}}, {"position": {"y": 125.33323356430454, "x": -992.1147013144778}, "data": {"depth": "2", "name": "\uc800\uc6b0\uc5b8\ub77c\uc774", "selected": false, "id": "42418"}}, {"position": {"y": 62.790519529313585, "x": -998.0267284282716}, "data": {"depth": "2", "name": "\ud6c4\uc9c4\ud0c0\uc624", "selected": false, "id": "34596"}}, {"position": {"y": 1.2246467991473532e-13, "x": -1000.0}, "data": {"depth": "2", "name": "\ub958\uc0ac\uc624\uce58", "selected": false, "id": "163794"}}, {"position": {"y": -62.79051952931334, "x": -998.0267284282716}, "data": {"depth": "2", "name": "\uc7a5\uce6d", "selected": false, "id": "164902"}}, {"position": {"y": -125.33323356430428, "x": -992.1147013144779}, "data": {"depth": "2", "name": "\uc479\uce6d\ub9c1", "selected": false, "id": "149475"}}, {"position": {"y": -187.3813145857243, "x": -982.2872507286887}, "data": {"depth": "2", "name": "\uc7a5\ucd98\ucc28\uc624", "selected": false, "id": "338125"}}, {"position": {"y": -248.68988716485458, "x": -968.5831611286312}, "data": {"depth": "2", "name": "\ub9b0\ubc4c\uc624", "selected": false, "id": "165332"}}, {"position": {"y": -309.0169943749473, "x": -951.0565162951536}, "data": {"depth": "2", "name": "\ud5c8\uad88\ucc3d", "selected": false, "id": "137872"}}, {"position": {"y": -368.1245526846779, "x": -929.7764858882515}, "data": {"depth": "2", "name": "\uc655\ud6d9\uc6d0", "selected": false, "id": "337698"}}, {"position": {"y": -425.77929156507264, "x": -904.8270524660195}, "data": {"depth": "2", "name": "\ud654\uad88\ud391", "selected": false, "id": "138933"}}, {"position": {"y": -481.753674101715, "x": -876.3066800438637}, "data": {"depth": "2", "name": "\uc800\uc6b0\uc5b8\ub77c\uc774", "selected": false, "id": "42418"}}, {"position": {"y": -535.8267949789964, "x": -844.3279255020152}, "data": {"depth": "2", "name": "\ud669\uc950", "selected": false, "id": "101637"}}, {"position": {"y": -587.785252292473, "x": -809.0169943749474}, "data": {"depth": "2", "name": "\ub9ac\ud391", "selected": false, "id": "138687"}}, {"position": {"y": -637.4239897486897, "x": -770.5132427757893}, "data": {"depth": "2", "name": "\uc8fc\ub8fd\uc9c0", "selected": false, "id": "41371"}}, {"position": {"y": -684.5471059286888, "x": -728.9686274214115}, "data": {"depth": "2", "name": "\uc800\uc6b0\uc5b8\ub77c\uc774", "selected": false, "id": "42418"}}, {"position": {"y": -728.9686274214114, "x": -684.5471059286889}, "data": {"depth": "2", "name": "\uc7a5\uca4c\ubbfc", "selected": false, "id": "2577"}}, {"position": {"y": -770.5132427757893, "x": -637.4239897486896}, "data": {"depth": "2", "name": "\ud6c4\uc9c4\ud0c0\uc624", "selected": false, "id": "34596"}}, {"position": {"y": -809.0169943749473, "x": -587.7852522924733}, "data": {"depth": "2", "name": "\uc2dc\uc9c4\ud551", "selected": false, "id": "139722"}}, {"position": {"y": -844.3279255020148, "x": -535.8267949789971}, "data": {"depth": "2", "name": "\uc790\uc624\ucbd4\uc591", "selected": false, "id": "11483"}}, {"position": {"y": -876.3066800438636, "x": -481.75367410171526}, "data": {"depth": "2", "name": "\ub958\uc0ac\uc624\uce58", "selected": false, "id": "163794"}}, {"position": {"y": -904.8270524660194, "x": -425.7792915650729}, "data": {"depth": "2", "name": "\ub9ac\ucee4\ucc3d", "selected": false, "id": "139742"}}, {"position": {"y": -929.7764858882515, "x": -368.1245526846778}, "data": {"depth": "2", "name": "\uca61\uce6d\ud6d9", "selected": false, "id": "138204"}}, {"position": {"y": -951.0565162951535, "x": -309.01699437494756}, "data": {"depth": "2", "name": "\ud391\ub354\ud654\uc774", "selected": false, "id": "166032"}}, {"position": {"y": -968.583161128631, "x": -248.6898871648553}, "data": {"depth": "2", "name": "\uc800\uc6b0\uc5b8\ub77c\uc774", "selected": false, "id": "42418"}}, {"position": {"y": -982.2872507286887, "x": -187.38131458572462}, "data": {"depth": "2", "name": "\uc7a5\uce6d", "selected": false, "id": "164902"}}, {"position": {"y": -992.1147013144778, "x": -125.33323356430459}, "data": {"depth": "2", "name": "\uc608\uc820\uc789", "selected": false, "id": "168460"}}, {"position": {"y": -998.0267284282716, "x": -62.79051952931321}, "data": {"depth": "2", "name": "\uc7a5\uad88\ud0c0\uc624", "selected": false, "id": "167374"}}, {"position": {"y": -1000.0, "x": -1.8369701987210297e-13}, "data": {"depth": "2", "name": "\uc8fc\ub354", "selected": false, "id": "164095"}}, {"position": {"y": -998.0267284282716, "x": 62.79051952931283}, "data": {"depth": "2", "name": "\ub958\uc0ac\uc624\uce58", "selected": false, "id": "163794"}}, {"position": {"y": -992.1147013144779, "x": 125.33323356430424}, "data": {"depth": "2", "name": "\ub9c8\uc624\uca4c\ub465", "selected": false, "id": "81426"}}, {"position": {"y": -982.2872507286887, "x": 187.38131458572425}, "data": {"depth": "2", "name": "\ub369\uc0e4\uc624\ud551", "selected": false, "id": "468"}}, {"position": {"y": -968.5831611286311, "x": 248.68988716485492}, "data": {"depth": "2", "name": "\ud654\uad88\ud391", "selected": false, "id": "138933"}}, {"position": {"y": -951.0565162951536, "x": 309.0169943749472}, "data": {"depth": "2", "name": "\uc8fc\ub8fd\uc9c0", "selected": false, "id": "41371"}}, {"position": {"y": -929.7764858882516, "x": 368.12455268467744}, "data": {"depth": "2", "name": "\uc800\uc6b0\uc5b8\ub77c\uc774", "selected": false, "id": "42418"}}, {"position": {"y": -904.8270524660196, "x": 425.7792915650726}, "data": {"depth": "2", "name": "\uc2dc\uc9c4\ud551", "selected": false, "id": "139722"}}, {"position": {"y": -876.3066800438638, "x": 481.7536741017149}, "data": {"depth": "2", "name": "\ub958\uc0ac\uc624\uce58", "selected": false, "id": "163794"}}, {"position": {"y": -844.327925502015, "x": 535.8267949789968}, "data": {"depth": "2", "name": "\uc7a5\uca4c\ubbfc", "selected": false, "id": "2577"}}, {"position": {"y": -809.0169943749476, "x": 587.7852522924729}, "data": {"depth": "2", "name": "\ub369\uc0e4\uc624\ud551", "selected": false, "id": "468"}}, {"position": {"y": -770.5132427757895, "x": 637.4239897486893}, "data": {"depth": "2", "name": "\ub9ac\ucc3d\ucd98", "selected": false, "id": "138941"}}, {"position": {"y": -728.9686274214115, "x": 684.5471059286887}, "data": {"depth": "2", "name": "\uca61\uce6d\ud6d9", "selected": false, "id": "138204"}}, {"position": {"y": -684.5471059286889, "x": 728.9686274214113}, "data": {"depth": "2", "name": "\uc7a5\ub354\uc7a5", "selected": false, "id": "760184"}}, {"position": {"y": -637.4239897486897, "x": 770.5132427757893}, "data": {"depth": "2", "name": "\ud669\uc950", "selected": false, "id": "101637"}}, {"position": {"y": -587.7852522924734, "x": 809.0169943749473}, "data": {"depth": "2", "name": "\ub9ac\ub354\uc131", "selected": false, "id": "882572"}}, {"position": {"y": -535.8267949789971, "x": 844.3279255020148}, "data": {"depth": "2", "name": "\ub7f0\ube44\uc2a4", "selected": false, "id": "890728"}}, {"position": {"y": -481.7536741017153, "x": 876.3066800438636}, "data": {"depth": "2", "name": "\uc57c\uc624\uc774\ub9b0", "selected": false, "id": "881187"}}, {"position": {"y": -425.779291565073, "x": 904.8270524660194}, "data": {"depth": "2", "name": "\ub9ac\ub780\uce6d", "selected": false, "id": "875149"}}, {"position": {"y": -368.12455268467784, "x": 929.7764858882515}, "data": {"depth": "2", "name": "\ub9ac\ud478\ucd98", "selected": false, "id": "882608"}}, {"position": {"y": -309.01699437494767, "x": 951.0565162951535}, "data": {"depth": "2", "name": "\uce89\uc131", "selected": false, "id": "167319"}}, {"position": {"y": -248.68988716485535, "x": 968.583161128631}, "data": {"depth": "2", "name": "\ub465\ube44\uc6b0", "selected": false, "id": "163964"}}, {"position": {"y": -187.38131458572468, "x": 982.2872507286887}, "data": {"depth": "2", "name": "\uc655\ub465\uc2f1", "selected": false, "id": "882080"}}, {"position": {"y": -125.33323356430465, "x": 992.1147013144778}, "data": {"depth": "2", "name": "\uc8fc\ub354", "selected": false, "id": "164095"}}, {"position": {"y": -62.790519529313265, "x": 998.0267284282716}, "data": {"depth": "2", "name": "\ub904\uac04", "selected": false, "id": "393695"}}]}, "data": {"__Annotations": [], "name": "ko-wiki-pageNetwork", "selected": true, "shared_name": "ko-wiki-pageNetwork"}}